{
"type": "FeatureCollection",
"name": "kleiderbeutel",
"crs": { "type": "name", "properties": { "name": "urn:ogc:def:crs:OGC:1.3:CRS84" } },
"features": [
{ "type": "Feature", "properties": { "id": null }, "geometry": { "type": "Point", "coordinates": [ 7.207272229716049, 50.796898586078036 ] } }
]
}
