{
"type": "FeatureCollection",
"name": "startunterlagen",
"crs": { "type": "name", "properties": { "name": "urn:ogc:def:crs:OGC:1.3:CRS84" } },
"features": [
{ "type": "Feature", "properties": { "id": null, "typ": "Startunterlagen", "info": "Stadtmuseum Siegburg\n Markt 46\n Ausgabe der Unterlagen\n Samstag 13-18Uhr\n Sonntag ab 9Uhr" }, "geometry": { "type": "Point", "coordinates": [ 7.206308652664033, 50.796255832846612 ] } }
]
}
