{
"type": "FeatureCollection",
"name": "verbot",
"crs": { "type": "name", "properties": { "name": "urn:ogc:def:crs:OGC:1.3:CRS84" } },
"features": [
{ "type": "Feature", "properties": { "id": null }, "geometry": { "type": "Point", "coordinates": [ 7.228465474313685, 50.791758108264091 ] } },
{ "type": "Feature", "properties": { "id": null }, "geometry": { "type": "Point", "coordinates": [ 7.212865008772115, 50.790192262280364 ] } },
{ "type": "Feature", "properties": { "id": null }, "geometry": { "type": "Point", "coordinates": [ 7.207210564941993, 50.792454039812412 ] } },
{ "type": "Feature", "properties": { "id": null }, "geometry": { "type": "Point", "coordinates": [ 7.207065579202759, 50.801399659923156 ] } },
{ "type": "Feature", "properties": { "id": null }, "geometry": { "type": "Point", "coordinates": [ 7.21083520842284, 50.802342067228167 ] } },
{ "type": "Feature", "properties": { "id": null }, "geometry": { "type": "Point", "coordinates": [ 7.217678535314681, 50.798151979364313 ] } },
{ "type": "Feature", "properties": { "id": null }, "geometry": { "type": "Point", "coordinates": [ 7.22228908182232, 50.796919600580821 ] } },
{ "type": "Feature", "properties": { "id": null }, "geometry": { "type": "Point", "coordinates": [ 7.225159799459152, 50.795484241762409 ] } }
]
}
